<?xml version="1.0" encoding="utf-8" standalone="yes" ?>
<T3locallang>
    <meta type="array">
        <description>locallang</description>
        <type>module</type>
        <csh_table></csh_table>
        <labelContext type="array">
        </labelContext>
    </meta>
    <data type="array">
        <languageKey index="default" type="array">
            <label index="total">Total</label>
            <label index="pi1_title">FE Edition Meta</label>
            <label index="pi1_plus_wiz_description">Adds a frontend form for submitting and editing of tables to your page</label>
            <label index="back_label">Back</label>
            <label index="new_label">New</label>
            <label index="fulltext_search">Fulltext search</label>
            <label index="alphabetical_search">Alphabetical search</label>
            <label index="calendar_search">Calendar search</label>
            <label index="order_by">Ordered by</label>
            <label index="login_required_message">Frontend login is required to view this page</label>
            <label index="edit_header_prefix">Editing of</label>
            <label index="grid_rows_cols">Rows / Cols </label>
            <label index="grid_header">Data Grid</label>
            <label index="crdate">Creation date</label>
            <label index="uid">Unique Identifier</label>
            <label index="pid">Page ID</label>
            <label index="sorting">Sorting Index</label>
            <label index="edit_grid_description">You may edit Grid Data here</label>
            <label index="edit_delete_label">Delete</label>
            <label index="edit_order_up_label">Move up Record</label>
            <label index="edit_order_down_label">Move down Record</label>
            <label index="edit_delete_confirm">Are you sure?</label>
            <label index="edit_saved_header">Saved</label>
            <label index="edit_saved_message">Your record has been saved</label>
            <label index="edit_preview_submit_label">Save changes</label>
            <label index="edit_preview_donotsave_label">Go Back</label>
            <label index="edit_submit_label">See Preview</label>
            <label index="edit_menu_header">Edit menu</label>
            <label index="edit_link">Edit record</label>
            <label index="filtre_recherche">Search Filter</label>
            <label index="filtre_lettre">Alphabetical Filter</label>
            <label index="blog_header">Comments of </label>
            <label index="blog_new_comment">Leave a comment</label>
            <label index="blog_submit_label">Leave my comment</label>
            <label index="blog_captcha_error">The anti-spam value is not the one shown in the image</label>
            <label index="link-edit">Edit record</label>
            <label index="link-consult">View this record</label>
            <label index="edit_menu_description">List of items</label>
            <label index="edit_menu_noitems_header">No items aval.</label>
            <label index="edit_menu_noitems_description">Sorry, there where no items available.</label>
            <label index="edit_menu_createnew_label">Create new record</label>
            <label index="alphabetical_search_all">All</label>
            <label index="advanced_search_label">Search</label>
            <label index="advanced_search_reset">Reset search criteria</label>
            <label index="order_by_reset">Reset order by</label>
            <label index="add_image_tooltip">Click here to browse your computer for a file to upload</label>
            <label index="delete_image_tooltip">Click here to delete a file you selected in the panel. To delete effectively you must save the modification </label>
            <label index="create_header_prefix">Create </label>
            <label index="create_saved_header">Added</label>
            <label index="create_saved_message">Your record has been added</label>
            <label index="create_preview_submit_label">Submit record</label>
            <label index="create_preview_donotsave_label">Do Not Save</label>
            <label index="create_edit_link">Edit a record</label>
            <label index="create_submit_label">See Preview</label>
            <label index="delete_saved_header">Deleted</label>
            <label index="delete_saved_message">The record has been deleted</label>
            <label index="delete_preview_header">Really want to delete the record?</label>
            <label index="delete_preview_message">If you delete the record it will be gone forever. So make sure you relly want to delete it?</label>
            <label index="delete_preview_delete_label">Yes, delete the record.</label>
            <label index="delete_preview_dont_delete_label">No, let me get back.</label>
            <label index="required_message">This field is required</label>
            <label index="error_file_size">Size is beyond %s kb ( %s bytes) and the file cannot be saved.</label>
            <label index="error_file_upload">Surprisingly there was no file for %s in %s</label>
            <label index="error_file_extension">Extension %s not allowed</label>
            <label index="error_file_pattern">Filename matched illegal pattern.</label>
            <label index="error_no_upload_path">No upload path defined !</label>
            <label index="error_occured">An error has arised, check your fields please</label>
            <label index="error_mvalue_existed">A record with the same values exists already. Maybe you clicked twice ...</label>
            <label index="error_value_existed">The value existed already. Enter a new value.</label>
            <label index="error_value_twice">You must enter the same value twice</label>
            <label index="error_valid_email">You must enter a valid email address</label>
            <label index="error_value_required">You must enter a value!</label>
            <label index="error_max_char">You must enter at most %s characters!</label>
            <label index="error_min_char">You must enter at least %s characters!</label>
            <label index="error_value_notInList">The value was not a valid value from this list: %s</label>
            <label index="error_required">A requested field is empty, check your fields !</label>
            <label index="blogcomments">Comments</label>
            <label index="monday">Monday</label>
            <label index="tuesday">Tuesday</label>
            <label index="wednesday">Wednesday</label>
            <label index="thursday">Thursday</label>
            <label index="friday">Friday</label>
            <label index="saturday">Saturday</label>
            <label index="sunday">Sunday</label>
            <label index="view_posts">View posts for %s</label>
            <label index="calReset">Reset</label>
            <label index="check_yes">Yes</label>
            <label index="check_no">No</label>
            <label index="search_nothing">None</label>
            <label index="move_top">Move selected items to top</label>
            <label index="move_up">Move selected items upwards</label>
            <label index="move_bt">Move selected items downwards</label>
            <label index="move_down">Move selected items to bottom</label>
            <label index="move_delete">Delete selected items</label>
            <label index="printedby">Printed by : </label>
            <label index="nbpages">Nb pages : </label>
            <label index="gotopage">Goto page : </label>
            <label index="nbrows">Nb rows : </label>
        </languageKey>
        
        <languageKey index="de" type="array">
            <label index="total">Total</label>
            <label index="pi1_title">FE Edition Meta</label>
            <label index="pi1_plus_wiz_description">Adds a frontend form for submitting and editing of tables to your page</label>
            <label index="back_label">Zurück</label>
            <label index="new_label">Neu</label>
            <label index="fulltext_search">Volltextsuche</label>
            <label index="alphabetical_search">Alphabetische Suche</label>
            <label index="calendar_search">Kalender Suche</label>
            <label index="order_by">Angefordert von</label>
            <label index="login_required_message">Sie müssen angemeldet sein, um diese Seite zu sehen</label>
            <label index="edit_header_prefix">Erstellung von</label>
            <label index="grid_rows_cols">Zeilen / Spalten </label>
            <label index="grid_header">Data Grid</label>
            <label index="crdate">Erstellungsdatum</label>
            <label index="uid">Unique Identifier</label>
            <label index="pid">Page ID</label>
            <label index="sorting">Sorting Index</label>
            <label index="edit_grid_description">You may edit Grid Data here</label>
            <label index="edit_delete_label">Löschen</label>
            <label index="edit_order_up_label">Nach oben</label>
            <label index="edit_order_down_label">Nach unten</label>
            <label index="edit_delete_confirm">Sind Sie sicher?</label>
            <label index="edit_saved_header">Gespeichert</label>
            <label index="edit_saved_message">Ihre Eingaben wurden gespeichert</label>
            <label index="edit_preview_submit_label">Änderungen speichern</label>
            <label index="edit_preview_donotsave_label">Zurück gehen</label>
            <label index="edit_submit_label">Vorschau</label>
            <label index="edit_menu_header">Bearbeiten Ihrer Einträge</label>
            <label index="edit_link">Bearbeiten</label>
            <label index="filtre_recherche">Suchfilter</label>
            <label index="filtre_lettre">Alphabetischer Filter</label>
            <label index="blog_header">Kommentar von: </label>
            <label index="blog_new_comment">Kommentieren</label>
            <label index="blog_submit_label">Leave my comment</label>
            <label index="blog_captcha_error">The anti-spam value is not the one shown in the image</label>
            <label index="link-edit">Bearbeiten</label>
            <label index="link-consult">Diesen Datensatz anschauen</label>
            <label index="edit_menu_description">Liste der angelegten Daten</label>
            <label index="edit_menu_noitems_header">Keine Daten verfügbar</label>
            <label index="edit_menu_noitems_description">Leider sind keine Daten verfügbar.</label>
            <label index="edit_menu_createnew_label">Neuen Datensatz anlegen</label>
            <label index="alphabetical_search_all">Alle</label>
            <label index="advanced_search_label">Suche</label>
            <label index="advanced_search_reset">Suchkriterium zurücksetzen</label>
            <label index="order_by_reset">Reset order by</label>
            <label index="add_image_tooltip">Hier klicken um eine Datei von Ihrem Rechner hoch zu laden</label>
            <label index="delete_image_tooltip">Klicken Sie hier um eine Datei, die Sie ausgewählt habenzu löschen. Um sie effectiv zu löschen, müssen Sie die Modifzierung zuvor sichern. </label>
            <label index="create_header_prefix">Erstellen</label>
            <label index="create_saved_header">Hinzugefügt</label>
            <label index="create_saved_message">Ihr Datensatz wurde hinzugefügt</label>
            <label index="create_preview_submit_label">Abschicken</label>
            <label index="create_preview_donotsave_label">Nicht speichern</label>
            <label index="create_edit_link">Einen Datensatz bearbeiten</label>
            <label index="create_submit_label">Vorschau</label>
            <label index="delete_saved_header">Gelöscht</label>
            <label index="delete_saved_message">Der Datensatz wurde gelöscht</label>
            <label index="delete_preview_header">Den Datensatz wirklich löschen?</label>
            <label index="delete_preview_message">Die Löschung des Datensatzes ist endgültig. Wollen Sie Ihn wirlich löschen?</label>
            <label index="delete_preview_delete_label">Ja, Datensatz löschen.</label>
            <label index="delete_preview_dont_delete_label">Nein, zurück.</label>
            <label index="required_message">Dies ist ein Mussfeld</label>
            <label index="error_file_size">Dateigröße ist mehr als %s kb ( %s bytes). Die Datei kann nicht gespeichert werden.</label>
            <label index="error_file_upload">Surprisingly there was no file for %s in %s</label>
            <label index="error_file_extension">Erweiterung %s nicht erlaubt</label>
            <label index="error_file_pattern">Filename matched illegal pattern.</label>
            <label index="error_no_upload_path">Es wurde kein Uploadpfad angegeben !</label>
            <label index="error_occured">Ein Fehler ist aufgetreten, prüfen Sie Ihre Eingabefelder</label>
            <label index="error_mvalue_existed">Ein Datensatz mit dem selben Wert besteht bereits. Vielleicht haben Sie zweimal geklickt ...</label>
            <label index="error_value_existed">Dieser Wert besteht bereits. Geben Sie einen neuen Wert ein.</label>
            <label index="error_value_twice">Sie müssen den geichen Wert zweimal eingeben.</label>
            <label index="error_valid_email">Sie müssen eine gültige Email-Adresse eingeben</label>
            <label index="error_value_required">Sie müssen einen Wert eingeben!</label>
            <label index="error_max_char">Sie müssen mindestens %s Stellen eingeben!</label>
            <label index="error_min_char">You must enter at least %s characters!</label>
            <label index="error_value_notInList">Dieser Wert ist kein gültiger Wert von dieser Liste: %s</label>
            <label index="error_required">Ein Mussfeld ist leer, prüfen Sie Ihre Eingabefelder !</label>
            <label index="blogcomments">Kommentar</label>
            <label index="monday">Montag</label>
            <label index="tuesday">Dienstag</label>
            <label index="wednesday">Mittwoch</label>
            <label index="thursday">Donnerstag</label>
            <label index="friday">Freitag</label>
            <label index="saturday">Samstag</label>
            <label index="sunday">Sonntag</label>
            <label index="view_posts">View posts for %s</label>
            <label index="calReset">Zurücksetzen</label>
            <label index="check_yes">Ja</label>
            <label index="check_no">Nein</label>
            <label index="search_nothing">Nichts</label>
            <label index="move_top">Move selected items to top</label>
            <label index="move_up">Move selected items upwards</label>
            <label index="move_bt">Move selected items downwards</label>
            <label index="move_down">Move selected items to bottom</label>
            <label index="move_delete">Delete selected items</label>
            <label index="printedby">Printed by : </label>
            <label index="nbpages">Nb pages : </label>
            <label index="gotopage">Gehe zur Seite : </label>
            <label index="nbrows">Nb rows : </label>
        </languageKey>
        
        
        <languageKey index="fr" type="array">
            <label index="total">Total</label>
            <label index="crdate">Date de création</label>
            <label index="uid">identifiant unique</label>
            <label index="sorting">index de tri</label>
            <label index="pid">ID de page</label>
            <label index="ascending">ascendant</label>
            <label index="descending">descendant</label>
            <label index="tstamp">Date de modification</label>
            <label index="fulltext_search">Recherche plein texte</label>
            <label index="alphabetical_search">Recherche alphabétique</label>
            <label index="calendar_search">Recherche calendaire</label>
            <label index="order_by">Ordonné par</label>
            <label index="pi1_title">FE Edition Meta</label>
            <label index="pi1_plus_wiz_description">Adds a frontend form for submitting and editing of tables to your page.</label>
            <label index="pi_list_browseresults_displays">Affichage des enregistrements ###SPAN_BEGIN###%s &amp;agrave; %s&lt;/span&gt; sur ###SPAN_BEGIN###%s&lt;/span&gt;</label>
            <label index="pi_list_searchBox_search">Chercher</label>
            <label index="pi_list_browseresults_prev">&lt; Précédent</label>
            <label index="pi_list_browseresults_next">Suivant &gt;</label>
            <label index="pi_list_browseresults_page">Page</label>
            <label index="grid_rows_cols">Lignes / Colonnes </label>
            <label index="grid_header">Data Grid</label>
            <label index="edit_grid_description">Vous pouvez éditer les informations de la grille ici</label>
            <label index="back_label">Retour</label>
            <label index="new_label">Nouveau</label>
            <label index="login_required_message">Vous devez &amp;ecirc;tre connecté pour voir cette page.</label>
            <label index="filtre_recherche">Filtre Recherche</label>
            <label index="filtre_lettre">Filtre alphabétique</label>
            <label index="blog_header">Commentaires de </label>
            <label index="blog_new_comment">Laisser un commentaire</label>
            <label index="blog_submit_label">Laisser mon commentaire</label>
            <label index="blog_captcha_error">La valeur anti-spam saisie n'est pas celle de l'image</label>
            <label index="edit_header_prefix">Edition de</label>
            <label index="edit_delete_label">Supprimer</label>
            <label index="edit_order_up_label">Monter</label>
            <label index="edit_order_down_label">Descendre</label>
            <label index="edit_delete_confirm">&amp;Ecirc;tes vous s&amp;ucirc;r ?</label>
            <label index="edit_saved_header">Enregistré</label>
            <label index="edit_saved_message">Vos informations ont été mises &amp;agrave; jour.</label>
            <label index="edit_preview_submit_label">Mettre &amp;agrave; jour</label>
            <label index="edit_preview_donotsave_label">Annuler</label>
            <label index="edit_submit_label">Prévisualiser</label>
            <label index="advanced_search_label">Recherche</label>
            <label index="advanced_search_reset">Enlever critères de recherche</label>
            <label index="order_by_reset">Enlever tri</label>
            <label index="actions">Actions</label>
            <label index="alphabetical_search_all">Tous</label>
            <label index="edit_menu_header">Liste des éléments</label>
            <label index="edit_menu_description">Modifiez ou consultez vos enregistrements ci dessous</label>
            <label index="edit_menu_noitems_header">Aucun élément</label>
            <label index="edit_menu_noitems_description">Il n'y a aucun élément &amp;agrave; éditer.</label>
            <label index="edit_link">Editer</label>
            <label index="link-edit">Editer</label>
            <label index="link-consult">Consulter</label>
            <label index="error_file_size">La taille du fichier (%2$s octets) est supérieure au maximum autorisé : %1$s Ko, le fichier ne peut &amp;ecirc;tre enregistré</label>
            <label index="error_file_upload">Le fichier %s est introuvable dans %s</label>
            <label index="error_file_extension">L'extension %s n'est pas autorisée</label>
            <label index="error_file_pattern">Le nom du fichier suit un motif interdit.</label>
            <label index="error_no_upload_path">Le chemin d'upload n'est pas défini</label>
            <label index="error_occured">Une erreur s'est produite,vérifiez vos champs</label>
            <label index="error_mvalue_existed">Un enregistrement a déj&amp;agrave; été saisi avec les m&amp;ecirc;mes valeurs. Peut &amp;ecirc;tre avez vous cliqué 2 fois ... Saisissez une autre valeur </label>
            <label index="error_value_existed">Cette valeur existe déj&amp;agrave; et doit &amp;ecirc;tre unique. Saisissez une autre valeur </label>
            <label index="error_value_twice">Les valeurs saisies ne sont pas les m&amp;ecirc;mes, vous devez saisir la m&amp;ecirc;me valeur deux fois.</label>
            <label index="error_valid_email">Vous devez saisir une adresse de courriel valide</label>
            <label index="error_value_required">Vous devez saisir une valeur</label>
            <label index="error_max_char">Ce champ ne peut dépasser %s caract&amp;egrave;res.</label>
            <label index="error_min_char">Ce champ doit contenir un minimum de %s caract&amp;egrave;res.</label>
            <label index="error_value_notInList">Cette valeur n'est pas une valeur valide de cette liste: %s</label>
            <label index="error_required">Un champ requis est vide, vérifiez vos champs</label>
            <label index="edit_menu_createnew_label">Nouvel élément</label>
            <label index="add_image_tooltip">Cliquez ici pour ouvrir une fen&amp;ecirc;tre de sélection de fichiers sur votre ordinateur. Il faut ensuite mettre &amp;agrave; jour l'enregistrement pour que la modification soit prise en compte</label>
            <label index="delete_image_tooltip">Cliquez ici pour supprimer un fichier de la boite de sélection de gauche. Pour effectuer la suppression vous devez mettre &amp;agrave; jour ensuite l'enregistrement</label>
            <label index="create_header_prefix">Créer</label>
            <label index="create_saved_header">Ajouté</label>
            <label index="create_saved_message">Votre soumission a été ajoutée</label>
            <label index="create_preview_submit_label">Soumettre</label>
            <label index="create_preview_donotsave_label">Annuler</label>
            <label index="create_edit_link">Editer</label>
            <label index="create_submit_label">Prévisualiser</label>
            <label index="delete_saved_header">Supprimé</label>
            <label index="delete_saved_message">Votre enregistrement a été supprimé.</label>
            <label index="delete_preview_header">Voulez vous vraiment supprimer cet enregistrement ?</label>
            <label index="delete_preview_message">Si vous supprimez cet enregistrement il sera irrémédiablement perdu. &amp;Ecirc;tes vous certain de vouloir le supprimer?</label>
            <label index="delete_preview_delete_label">Oui, je veux supprimer mon enregistrement.</label>
            <label index="delete_preview_dont_delete_label">Non, je veux revenir &amp;agrave; l&amp;acute;edition de mes données.</label>
            <label index="required_message">Ce champ est requis.</label>
            <label index="blogcomments">Commentaires</label>
            <label index="monday">Lundi</label>
            <label index="tuesday">Mardi</label>
            <label index="wednesday">Mercredi</label>
            <label index="thursday">Jeudi</label>
            <label index="friday">Vendredi</label>
            <label index="saturday">Samedi</label>
            <label index="sunday">Dimanche</label>
            <label index="view_posts">Voir les enregistrements pour %s</label>
            <label index="calReset">Tout voir</label>
            <label index="check_yes">Oui</label>
            <label index="check_no">Non</label>
            <label index="search_nothing">Aucun</label>
            <label index="move_top">Déplacer vers le haut les éléments sélectionnés</label>
            <label index="move_up">Déplacer l'élément vers le haut</label>
            <label index="move_bt">Déplacer l'élément vers le bas</label>
            <label index="move_down">Déplacer l'élément en bas</label>
            <label index="move_delete">Supprimer les éléments sélectionnés</label>
            <label index="printedby">Imprimé par : </label>
            <label index="nbpages">Nb pages : </label>
            <label index="gotopage">Aller &amp;agrave; la page : </label>
            <label index="nbrows">Nb éléments : </label>
        </languageKey>
    </data>
    <orig_hash type="array">
        <languageKey index="default" type="array">
            <label index="total" type="integer">158007617</label>
            <label index="pi1_title" type="integer">216175142</label>
            <label index="pi1_plus_wiz_description" type="integer">81214133</label>
            <label index="back_label" type="integer">5603241</label>
            <label index="new_label" type="integer">3944062</label>
            <label index="fulltext_search" type="integer">58282590</label>
            <label index="alphabetical_search" type="integer">188222428</label>
            <label index="calendar_search" type="integer">216739397</label>
            <label index="order_by" type="integer">67515018</label>
            <label index="login_required_message" type="integer">147782069</label>
            <label index="edit_header_prefix" type="integer">138377840</label>
            <label index="grid_rows_cols" type="integer">245928003</label>
            <label index="grid_header" type="integer">66442986</label>
            <label index="crdate" type="integer">51454473</label>
            <label index="uid" type="integer">88566323</label>
            <label index="pid" type="integer">50799274</label>
            <label index="sorting" type="integer">196924774</label>
            <label index="edit_grid_description" type="integer">35955609</label>
            <label index="edit_delete_label" type="integer">254438473</label>
            <label index="edit_order_up_label" type="integer">212210717</label>
            <label index="edit_order_down_label" type="integer">232238061</label>
            <label index="edit_delete_confirm" type="integer">120169752</label>
            <label index="edit_saved_header" type="integer">38286177</label>
            <label index="edit_saved_message" type="integer">257172887</label>
            <label index="edit_preview_submit_label" type="integer">229272392</label>
            <label index="edit_preview_donotsave_label" type="integer">83031521</label>
            <label index="edit_submit_label" type="integer">166390502</label>
            <label index="edit_menu_header" type="integer">144795055</label>
            <label index="edit_link" type="integer">148343509</label>
            <label index="filtre_recherche" type="integer">189801653</label>
            <label index="filtre_lettre" type="integer">215734701</label>
            <label index="blog_header" type="integer">194536274</label>
            <label index="blog_new_comment" type="integer">81032549</label>
            <label index="blog_submit_label" type="integer">52144943</label>
            <label index="blog_captcha_error" type="integer">67355199</label>
            <label index="link-edit" type="integer">148343509</label>
            <label index="link-consult" type="integer">206783855</label>
            <label index="edit_menu_description" type="integer">266789160</label>
            <label index="edit_menu_noitems_header" type="integer">184672973</label>
            <label index="edit_menu_noitems_description" type="integer">4335095</label>
            <label index="edit_menu_createnew_label" type="integer">54021068</label>
            <label index="alphabetical_search_all" type="integer">186422474</label>
            <label index="advanced_search_label" type="integer">20138052</label>
            <label index="advanced_search_reset" type="integer">260914718</label>
            <label index="order_by_reset" type="integer">233086071</label>
            <label index="add_image_tooltip" type="integer">211810107</label>
            <label index="delete_image_tooltip" type="integer">109011283</label>
            <label index="create_header_prefix" type="integer">263775591</label>
            <label index="create_saved_header" type="integer">254401983</label>
            <label index="create_saved_message" type="integer">262154469</label>
            <label index="create_preview_submit_label" type="integer">178092183</label>
            <label index="create_preview_donotsave_label" type="integer">190841472</label>
            <label index="create_edit_link" type="integer">239212971</label>
            <label index="create_submit_label" type="integer">166390502</label>
            <label index="delete_saved_header" type="integer">100556805</label>
            <label index="delete_saved_message" type="integer">237646260</label>
            <label index="delete_preview_header" type="integer">258829699</label>
            <label index="delete_preview_message" type="integer">127579015</label>
            <label index="delete_preview_delete_label" type="integer">134312520</label>
            <label index="delete_preview_dont_delete_label" type="integer">264615269</label>
            <label index="required_message" type="integer">5316320</label>
            <label index="error_file_size" type="integer">234140058</label>
            <label index="error_file_upload" type="integer">92391974</label>
            <label index="error_file_extension" type="integer">107289546</label>
            <label index="error_file_pattern" type="integer">217051443</label>
            <label index="error_no_upload_path" type="integer">102739772</label>
            <label index="error_occured" type="integer">190684926</label>
            <label index="error_mvalue_existed" type="integer">79214</label>
            <label index="error_value_existed" type="integer">227560778</label>
            <label index="error_value_twice" type="integer">250735620</label>
            <label index="error_valid_email" type="integer">139339454</label>
            <label index="error_value_required" type="integer">48745476</label>
            <label index="error_max_char" type="integer">35494949</label>
            <label index="error_min_char" type="integer">100400175</label>
            <label index="error_value_notInList" type="integer">132554025</label>
            <label index="error_required" type="integer">193936071</label>
            <label index="blogcomments" type="integer">138493032</label>
            <label index="monday" type="integer">116937262</label>
            <label index="tuesday" type="integer">91824917</label>
            <label index="wednesday" type="integer">127320419</label>
            <label index="thursday" type="integer">126543600</label>
            <label index="friday" type="integer">204714296</label>
            <label index="saturday" type="integer">146212113</label>
            <label index="sunday" type="integer">164733076</label>
            <label index="view_posts" type="integer">180246946</label>
            <label index="calReset" type="integer">86431368</label>
            <label index="check_yes" type="integer">154974727</label>
            <label index="check_no" type="integer">196073266</label>
            <label index="search_nothing" type="integer">112064895</label>
            <label index="move_top" type="integer">234987422</label>
            <label index="move_up" type="integer">182650699</label>
            <label index="move_bt" type="integer">73063474</label>
            <label index="move_down" type="integer">34443035</label>
            <label index="move_delete" type="integer">193908484</label>
            <label index="printedby" type="integer">107391039</label>
            <label index="nbpages" type="integer">65105772</label>
            <label index="gotopage" type="integer">232712425</label>
            <label index="nbrows" type="integer">142411009</label>
        </languageKey>
        <languageKey index="fr" type="array">
            <label index="total" type="integer">158007617</label>
            <label index="crdate" type="integer">51454473</label>
            <label index="uid" type="integer">88566323</label>
            <label index="sorting" type="integer">196924774</label>
            <label index="pid" type="integer">50799274</label>
            <label index="ascending" type="integer">222419149</label>
            <label index="descending" type="integer">222419149</label>
            <label index="tstamp" type="integer">222419149</label>
            <label index="fulltext_search" type="integer">58282590</label>
            <label index="alphabetical_search" type="integer">188222428</label>
            <label index="calendar_search" type="integer">216739397</label>
            <label index="order_by" type="integer">67515018</label>
            <label index="pi1_title" type="integer">216175142</label>
            <label index="pi1_plus_wiz_description" type="integer">81214133</label>
            <label index="pi_list_browseresults_displays" type="integer">222419149</label>
            <label index="pi_list_searchBox_search" type="integer">222419149</label>
            <label index="pi_list_browseresults_prev" type="integer">222419149</label>
            <label index="pi_list_browseresults_next" type="integer">222419149</label>
            <label index="pi_list_browseresults_page" type="integer">222419149</label>
            <label index="grid_rows_cols" type="integer">245928003</label>
            <label index="grid_header" type="integer">66442986</label>
            <label index="edit_grid_description" type="integer">35955609</label>
            <label index="back_label" type="integer">5603241</label>
            <label index="new_label" type="integer">3944062</label>
            <label index="login_required_message" type="integer">147782069</label>
            <label index="filtre_recherche" type="integer">189801653</label>
            <label index="filtre_lettre" type="integer">215734701</label>
            <label index="blog_header" type="integer">194536274</label>
            <label index="blog_new_comment" type="integer">81032549</label>
            <label index="blog_submit_label" type="integer">52144943</label>
            <label index="blog_captcha_error" type="integer">67355199</label>
            <label index="edit_header_prefix" type="integer">138377840</label>
            <label index="edit_delete_label" type="integer">254438473</label>
            <label index="edit_order_up_label" type="integer">212210717</label>
            <label index="edit_order_down_label" type="integer">232238061</label>
            <label index="edit_delete_confirm" type="integer">120169752</label>
            <label index="edit_saved_header" type="integer">38286177</label>
            <label index="edit_saved_message" type="integer">257172887</label>
            <label index="edit_preview_submit_label" type="integer">229272392</label>
            <label index="edit_preview_donotsave_label" type="integer">83031521</label>
            <label index="edit_submit_label" type="integer">166390502</label>
            <label index="advanced_search_label" type="integer">20138052</label>
            <label index="advanced_search_reset" type="integer">260914718</label>
            <label index="order_by_reset" type="integer">233086071</label>
            <label index="actions" type="integer">222419149</label>
            <label index="alphabetical_search_all" type="integer">186422474</label>
            <label index="edit_menu_header" type="integer">144795055</label>
            <label index="edit_menu_description" type="integer">266789160</label>
            <label index="edit_menu_noitems_header" type="integer">184672973</label>
            <label index="edit_menu_noitems_description" type="integer">4335095</label>
            <label index="edit_link" type="integer">148343509</label>
            <label index="link-edit" type="integer">148343509</label>
            <label index="link-consult" type="integer">206783855</label>
            <label index="error_file_size" type="integer">234140058</label>
            <label index="error_file_upload" type="integer">92391974</label>
            <label index="error_file_extension" type="integer">107289546</label>
            <label index="error_file_pattern" type="integer">217051443</label>
            <label index="error_no_upload_path" type="integer">102739772</label>
            <label index="error_occured" type="integer">190684926</label>
            <label index="error_mvalue_existed" type="integer">79214</label>
            <label index="error_value_existed" type="integer">227560778</label>
            <label index="error_value_twice" type="integer">250735620</label>
            <label index="error_valid_email" type="integer">139339454</label>
            <label index="error_value_required" type="integer">48745476</label>
            <label index="error_max_char" type="integer">35494949</label>
            <label index="error_min_char" type="integer">100400175</label>
            <label index="error_value_notInList" type="integer">132554025</label>
            <label index="error_required" type="integer">193936071</label>
            <label index="edit_menu_createnew_label" type="integer">54021068</label>
            <label index="add_image_tooltip" type="integer">211810107</label>
            <label index="delete_image_tooltip" type="integer">109011283</label>
            <label index="create_header_prefix" type="integer">263775591</label>
            <label index="create_saved_header" type="integer">254401983</label>
            <label index="create_saved_message" type="integer">262154469</label>
            <label index="create_preview_submit_label" type="integer">178092183</label>
            <label index="create_preview_donotsave_label" type="integer">190841472</label>
            <label index="create_edit_link" type="integer">239212971</label>
            <label index="create_submit_label" type="integer">166390502</label>
            <label index="delete_saved_header" type="integer">100556805</label>
            <label index="delete_saved_message" type="integer">237646260</label>
            <label index="delete_preview_header" type="integer">258829699</label>
            <label index="delete_preview_message" type="integer">127579015</label>
            <label index="delete_preview_delete_label" type="integer">134312520</label>
            <label index="delete_preview_dont_delete_label" type="integer">264615269</label>
            <label index="required_message" type="integer">5316320</label>
            <label index="blogcomments" type="integer">138493032</label>
            <label index="monday" type="integer">116937262</label>
            <label index="tuesday" type="integer">91824917</label>
            <label index="wednesday" type="integer">127320419</label>
            <label index="thursday" type="integer">126543600</label>
            <label index="friday" type="integer">204714296</label>
            <label index="saturday" type="integer">146212113</label>
            <label index="sunday" type="integer">164733076</label>
            <label index="view_posts" type="integer">180246946</label>
            <label index="calReset" type="integer">86431368</label>
            <label index="check_yes" type="integer">154974727</label>
            <label index="check_no" type="integer">196073266</label>
            <label index="search_nothing" type="integer">112064895</label>
            <label index="move_top" type="integer">234987422</label>
            <label index="move_up" type="integer">182650699</label>
            <label index="move_bt" type="integer">73063474</label>
            <label index="move_down" type="integer">34443035</label>
            <label index="move_delete" type="integer">193908484</label>
            <label index="printedby" type="integer">107391039</label>
            <label index="nbpages" type="integer">65105772</label>
            <label index="gotopage" type="integer">232712425</label>
            <label index="nbrows" type="integer">142411009</label>
        </languageKey>
    </orig_hash>
    <orig_text type="array">
        <languageKey index="default" type="array">
        </languageKey>
        <languageKey index="fr" type="array">
        </languageKey>
    </orig_text>
</T3locallang>